<?xml version="1.0" encoding="utf-8"?>
<ode><userPreferences><userPreference><key>theme</key><value>base</value></userPreference></userPreferences><odeResources><odeResource><key>odeVersionId</key><value>20260201162128QPOWBY</value></odeResource><odeResource><key>odeId</key><value>20260201155208SKONMV</value></odeResource><odeResource><key>odeVersionName</key><value>0</value></odeResource><odeResource><key>isDownload</key><value>true</value></odeResource><odeResource><key>eXeVersion</key><value>v3.0.2</value></odeResource></odeResources><odeProperties><odeProperty><key>pp_title</key><value>Equacions</value></odeProperty><odeProperty><key>pp_subtitle</key><value>2n ESO. Tema 5</value></odeProperty><odeProperty><key>pp_lang</key><value>ca</value></odeProperty><odeProperty><key>pp_author</key><value>Pep M. Vila</value></odeProperty><odeProperty><key>license</key><value>creative commons: attribution - share alike 4.0</value></odeProperty><odeProperty><key>pp_description</key><value>Institut Martí Dot - 2025/2026</value></odeProperty><odeProperty><key>exportSource</key><value>true</value></odeProperty><odeProperty><key>pp_addExeLink</key><value>true</value></odeProperty><odeProperty><key>pp_addPagination</key><value>false</value></odeProperty><odeProperty><key>pp_addSearchBox</key><value>true</value></odeProperty><odeProperty><key>pp_addAccessibilityToolbar</key><value>false</value></odeProperty><odeProperty><key>pp_extraHeadContent</key><value/></odeProperty><odeProperty><key>footer</key><value/></odeProperty></odeProperties><odeNavStructures><odeNavStructure><odePageId>20260201162129LCNYYV</odePageId><odeParentPageId/><pageName>Inici</pageName><odeNavStructureOrder>1</odeNavStructureOrder><odeNavStructureProperties><odeNavStructureProperty><key>titleNode</key><value>Inici</value></odeNavStructureProperty><odeNavStructureProperty><key>hidePageTitle</key><value>false</value></odeNavStructureProperty><odeNavStructureProperty><key>titleHtml</key><value/></odeNavStructureProperty><odeNavStructureProperty><key>editableInPage</key><value>false</value></odeNavStructureProperty><odeNavStructureProperty><key>titlePage</key><value>Inici</value></odeNavStructureProperty><odeNavStructureProperty><key>visibility</key><value>true</value></odeNavStructureProperty><odeNavStructureProperty><key>highlight</key><value>false</value></odeNavStructureProperty><odeNavStructureProperty><key>description</key><value/></odeNavStructureProperty></odeNavStructureProperties><odePagStructures><odePagStructure><odePageId>20260201162129LCNYYV</odePageId><odeBlockId>20260201162129SKAUVT</odeBlockId><blockName>De què va aquest tema?</blockName><iconName/><odePagStructureOrder>1</odePagStructureOrder><odePagStructureProperties><odePagStructureProperty><key>visibility</key><value>true</value></odePagStructureProperty><odePagStructureProperty><key>teacherOnly</key><value>false</value></odePagStructureProperty><odePagStructureProperty><key>allowToggle</key><value>true</value></odePagStructureProperty><odePagStructureProperty><key>minimized</key><value>false</value></odePagStructureProperty><odePagStructureProperty><key>identifier</key><value/></odePagStructureProperty><odePagStructureProperty><key>cssClass</key><value/></odePagStructureProperty></odePagStructureProperties><odeComponents><odeComponent><odePageId>20260201162129LCNYYV</odePageId><odeBlockId>20260201162129SKAUVT</odeBlockId><odeIdeviceId>20260201165520457DXH</odeIdeviceId><odeIdeviceTypeName>text</odeIdeviceTypeName><htmlView>&lt;div class="exe-text-template"&gt;&lt;div class="textIdeviceContent"&gt;
            &lt;div class="exe-text-activity"&gt;
                &lt;div&gt;&lt;p&gt;Un dos, tres&lt;/p&gt;&lt;p class="clearfix"&gt;&lt;/p&gt;&lt;/div&gt;
            &lt;/div&gt;&lt;/div&gt;&lt;/div&gt;</htmlView><jsonProperties>{"ideviceId":"20260201165520457DXH","textInfoDurationInput":"","textInfoDurationTextInput":"Duración","textInfoParticipantsInput":"","textInfoParticipantsTextInput":"Agrupamiento","textTextarea":"&lt;p&gt;Un dos, tres&lt;/p&gt;","textFeedbackInput":"Mostra la retroacció","textFeedbackTextarea":""}</jsonProperties><odeComponentsOrder>1</odeComponentsOrder><odeComponentsProperties><odeComponentsProperty><key>visibility</key><value>true</value></odeComponentsProperty><odeComponentsProperty><key>teacherOnly</key><value>false</value></odeComponentsProperty><odeComponentsProperty><key>identifier</key><value/></odeComponentsProperty><odeComponentsProperty><key>cssClass</key><value/></odeComponentsProperty></odeComponentsProperties></odeComponent></odeComponents></odePagStructure></odePagStructures></odeNavStructure><odeNavStructure><odePageId>20260201162129EZOYHP</odePageId><odeParentPageId/><pageName>Teoria</pageName><odeNavStructureOrder>2</odeNavStructureOrder><odeNavStructureProperties><odeNavStructureProperty><key>titleNode</key><value/></odeNavStructureProperty><odeNavStructureProperty><key>hidePageTitle</key><value>false</value></odeNavStructureProperty><odeNavStructureProperty><key>titleHtml</key><value/></odeNavStructureProperty><odeNavStructureProperty><key>editableInPage</key><value>false</value></odeNavStructureProperty><odeNavStructureProperty><key>titlePage</key><value>Teoria</value></odeNavStructureProperty><odeNavStructureProperty><key>visibility</key><value>true</value></odeNavStructureProperty><odeNavStructureProperty><key>highlight</key><value>false</value></odeNavStructureProperty><odeNavStructureProperty><key>description</key><value/></odeNavStructureProperty></odeNavStructureProperties><odePagStructures><odePagStructure><odePageId>20260201162129EZOYHP</odePageId><odeBlockId>20260201162129QEOLNU</odeBlockId><blockName>Text</blockName><iconName/><odePagStructureOrder>1</odePagStructureOrder><odePagStructureProperties><odePagStructureProperty><key>visibility</key><value>true</value></odePagStructureProperty><odePagStructureProperty><key>teacherOnly</key><value>false</value></odePagStructureProperty><odePagStructureProperty><key>allowToggle</key><value>true</value></odePagStructureProperty><odePagStructureProperty><key>minimized</key><value>false</value></odePagStructureProperty><odePagStructureProperty><key>identifier</key><value/></odePagStructureProperty><odePagStructureProperty><key>cssClass</key><value/></odePagStructureProperty></odePagStructureProperties><odeComponents><odeComponent><odePageId>20260201162129EZOYHP</odePageId><odeBlockId>20260201162129QEOLNU</odeBlockId><odeIdeviceId>20260201172044668QMP</odeIdeviceId><odeIdeviceTypeName>text</odeIdeviceTypeName><htmlView>&lt;div class="exe-text-template"&gt;&lt;div class="textIdeviceContent"&gt;
            &lt;div class="exe-text-activity"&gt;
                &lt;div&gt;&lt;p&gt;Prooova&lt;/p&gt;
&lt;p&gt;&lt;/p&gt;&lt;p class="clearfix"&gt;&lt;/p&gt;&lt;/div&gt;
            &lt;/div&gt;&lt;/div&gt;&lt;/div&gt;</htmlView><jsonProperties>{"ideviceId":"20260201172044668QMP","textInfoDurationInput":"","textInfoDurationTextInput":"Duration","textInfoParticipantsInput":"","textInfoParticipantsTextInput":"Grouping","textTextarea":"&lt;p&gt;Prooova&lt;/p&gt;\n&lt;p&gt;&lt;/p&gt;","textFeedbackInput":"Mostra la retroacció","textFeedbackTextarea":""}</jsonProperties><odeComponentsOrder>1</odeComponentsOrder><odeComponentsProperties><odeComponentsProperty><key>visibility</key><value>true</value></odeComponentsProperty><odeComponentsProperty><key>teacherOnly</key><value>false</value></odeComponentsProperty><odeComponentsProperty><key>identifier</key><value/></odeComponentsProperty><odeComponentsProperty><key>cssClass</key><value/></odeComponentsProperty></odeComponentsProperties></odeComponent></odeComponents></odePagStructure></odePagStructures></odeNavStructure><odeNavStructure><odePageId>20260201162129VKFXUH</odePageId><odeParentPageId/><pageName>Tipus d'Equacions</pageName><odeNavStructureOrder>3</odeNavStructureOrder><odeNavStructureProperties><odeNavStructureProperty><key>titleNode</key><value/></odeNavStructureProperty><odeNavStructureProperty><key>hidePageTitle</key><value>false</value></odeNavStructureProperty><odeNavStructureProperty><key>titleHtml</key><value/></odeNavStructureProperty><odeNavStructureProperty><key>editableInPage</key><value>false</value></odeNavStructureProperty><odeNavStructureProperty><key>titlePage</key><value>Tipus d'Equacions</value></odeNavStructureProperty><odeNavStructureProperty><key>visibility</key><value>true</value></odeNavStructureProperty><odeNavStructureProperty><key>highlight</key><value>false</value></odeNavStructureProperty><odeNavStructureProperty><key>description</key><value/></odeNavStructureProperty></odeNavStructureProperties><odePagStructures/></odeNavStructure><odeNavStructure><odePageId>20260201162129MASKDH</odePageId><odeParentPageId/><pageName>Equacions de Primer Grau</pageName><odeNavStructureOrder>4</odeNavStructureOrder><odeNavStructureProperties><odeNavStructureProperty><key>titleNode</key><value/></odeNavStructureProperty><odeNavStructureProperty><key>hidePageTitle</key><value>false</value></odeNavStructureProperty><odeNavStructureProperty><key>titleHtml</key><value/></odeNavStructureProperty><odeNavStructureProperty><key>editableInPage</key><value>false</value></odeNavStructureProperty><odeNavStructureProperty><key>titlePage</key><value>Equacions de Primer Grau</value></odeNavStructureProperty><odeNavStructureProperty><key>visibility</key><value>true</value></odeNavStructureProperty><odeNavStructureProperty><key>highlight</key><value>false</value></odeNavStructureProperty><odeNavStructureProperty><key>description</key><value/></odeNavStructureProperty></odeNavStructureProperties><odePagStructures/></odeNavStructure><odeNavStructure><odePageId>20260201162129GZXZJF</odePageId><odeParentPageId/><pageName>Equacions de Segon Grau</pageName><odeNavStructureOrder>5</odeNavStructureOrder><odeNavStructureProperties><odeNavStructureProperty><key>titleNode</key><value/></odeNavStructureProperty><odeNavStructureProperty><key>hidePageTitle</key><value>false</value></odeNavStructureProperty><odeNavStructureProperty><key>titleHtml</key><value/></odeNavStructureProperty><odeNavStructureProperty><key>editableInPage</key><value>false</value></odeNavStructureProperty><odeNavStructureProperty><key>titlePage</key><value>Equacions de Segon Grau</value></odeNavStructureProperty><odeNavStructureProperty><key>visibility</key><value>true</value></odeNavStructureProperty><odeNavStructureProperty><key>highlight</key><value>false</value></odeNavStructureProperty><odeNavStructureProperty><key>description</key><value/></odeNavStructureProperty></odeNavStructureProperties><odePagStructures/></odeNavStructure><odeNavStructure><odePageId>20260201162129XOWUVZ</odePageId><odeParentPageId/><pageName>Problemes d'Equacions</pageName><odeNavStructureOrder>6</odeNavStructureOrder><odeNavStructureProperties><odeNavStructureProperty><key>titleNode</key><value/></odeNavStructureProperty><odeNavStructureProperty><key>hidePageTitle</key><value>false</value></odeNavStructureProperty><odeNavStructureProperty><key>titleHtml</key><value/></odeNavStructureProperty><odeNavStructureProperty><key>editableInPage</key><value>false</value></odeNavStructureProperty><odeNavStructureProperty><key>titlePage</key><value>Problemes d'Equacions</value></odeNavStructureProperty><odeNavStructureProperty><key>visibility</key><value>true</value></odeNavStructureProperty><odeNavStructureProperty><key>highlight</key><value>false</value></odeNavStructureProperty><odeNavStructureProperty><key>description</key><value/></odeNavStructureProperty></odeNavStructureProperties><odePagStructures/></odeNavStructure><odeNavStructure><odePageId>20260201162129ZMSYSM</odePageId><odeParentPageId>20260201162129MASKDH</odeParentPageId><pageName>Sense parèntesis, sense fraccions</pageName><odeNavStructureOrder>1</odeNavStructureOrder><odeNavStructureProperties><odeNavStructureProperty><key>titleNode</key><value/></odeNavStructureProperty><odeNavStructureProperty><key>hidePageTitle</key><value>false</value></odeNavStructureProperty><odeNavStructureProperty><key>titleHtml</key><value/></odeNavStructureProperty><odeNavStructureProperty><key>editableInPage</key><value>false</value></odeNavStructureProperty><odeNavStructureProperty><key>titlePage</key><value>Sense parèntesis, sense fraccions</value></odeNavStructureProperty><odeNavStructureProperty><key>visibility</key><value>true</value></odeNavStructureProperty><odeNavStructureProperty><key>highlight</key><value>false</value></odeNavStructureProperty><odeNavStructureProperty><key>description</key><value/></odeNavStructureProperty></odeNavStructureProperties><odePagStructures/></odeNavStructure><odeNavStructure><odePageId>20260201162129MAMEHK</odePageId><odeParentPageId>20260201162129MASKDH</odeParentPageId><pageName>Amb parèntesis</pageName><odeNavStructureOrder>2</odeNavStructureOrder><odeNavStructureProperties><odeNavStructureProperty><key>titleNode</key><value/></odeNavStructureProperty><odeNavStructureProperty><key>hidePageTitle</key><value>false</value></odeNavStructureProperty><odeNavStructureProperty><key>titleHtml</key><value/></odeNavStructureProperty><odeNavStructureProperty><key>editableInPage</key><value>false</value></odeNavStructureProperty><odeNavStructureProperty><key>titlePage</key><value>Amb parèntesis</value></odeNavStructureProperty><odeNavStructureProperty><key>visibility</key><value>true</value></odeNavStructureProperty><odeNavStructureProperty><key>highlight</key><value>false</value></odeNavStructureProperty><odeNavStructureProperty><key>description</key><value/></odeNavStructureProperty></odeNavStructureProperties><odePagStructures/></odeNavStructure><odeNavStructure><odePageId>20260201162129GWCXVV</odePageId><odeParentPageId>20260201162129MASKDH</odeParentPageId><pageName>Amb fraccions</pageName><odeNavStructureOrder>3</odeNavStructureOrder><odeNavStructureProperties><odeNavStructureProperty><key>titleNode</key><value/></odeNavStructureProperty><odeNavStructureProperty><key>hidePageTitle</key><value>false</value></odeNavStructureProperty><odeNavStructureProperty><key>titleHtml</key><value/></odeNavStructureProperty><odeNavStructureProperty><key>editableInPage</key><value>false</value></odeNavStructureProperty><odeNavStructureProperty><key>titlePage</key><value>Amb fraccions</value></odeNavStructureProperty><odeNavStructureProperty><key>visibility</key><value>true</value></odeNavStructureProperty><odeNavStructureProperty><key>highlight</key><value>false</value></odeNavStructureProperty><odeNavStructureProperty><key>description</key><value/></odeNavStructureProperty></odeNavStructureProperties><odePagStructures/></odeNavStructure><odeNavStructure><odePageId>20260201162129SADKCB</odePageId><odeParentPageId>20260201162129MASKDH</odeParentPageId><pageName>Mètode general</pageName><odeNavStructureOrder>4</odeNavStructureOrder><odeNavStructureProperties><odeNavStructureProperty><key>titleNode</key><value/></odeNavStructureProperty><odeNavStructureProperty><key>hidePageTitle</key><value>false</value></odeNavStructureProperty><odeNavStructureProperty><key>titleHtml</key><value/></odeNavStructureProperty><odeNavStructureProperty><key>editableInPage</key><value>false</value></odeNavStructureProperty><odeNavStructureProperty><key>titlePage</key><value>Mètode general</value></odeNavStructureProperty><odeNavStructureProperty><key>visibility</key><value>true</value></odeNavStructureProperty><odeNavStructureProperty><key>highlight</key><value>false</value></odeNavStructureProperty><odeNavStructureProperty><key>description</key><value/></odeNavStructureProperty></odeNavStructureProperties><odePagStructures/></odeNavStructure><odeNavStructure><odePageId>20260201162129CTUIYD</odePageId><odeParentPageId>20260201162129GZXZJF</odeParentPageId><pageName>Fàcils</pageName><odeNavStructureOrder>1</odeNavStructureOrder><odeNavStructureProperties><odeNavStructureProperty><key>titleNode</key><value/></odeNavStructureProperty><odeNavStructureProperty><key>hidePageTitle</key><value>false</value></odeNavStructureProperty><odeNavStructureProperty><key>titleHtml</key><value/></odeNavStructureProperty><odeNavStructureProperty><key>editableInPage</key><value>false</value></odeNavStructureProperty><odeNavStructureProperty><key>titlePage</key><value>Fàcils</value></odeNavStructureProperty><odeNavStructureProperty><key>visibility</key><value>true</value></odeNavStructureProperty><odeNavStructureProperty><key>highlight</key><value>false</value></odeNavStructureProperty><odeNavStructureProperty><key>description</key><value/></odeNavStructureProperty></odeNavStructureProperties><odePagStructures/></odeNavStructure><odeNavStructure><odePageId>20260201162129MTWVTG</odePageId><odeParentPageId>20260201162129GZXZJF</odeParentPageId><pageName>Mètode general</pageName><odeNavStructureOrder>2</odeNavStructureOrder><odeNavStructureProperties><odeNavStructureProperty><key>titleNode</key><value/></odeNavStructureProperty><odeNavStructureProperty><key>hidePageTitle</key><value>false</value></odeNavStructureProperty><odeNavStructureProperty><key>titleHtml</key><value/></odeNavStructureProperty><odeNavStructureProperty><key>editableInPage</key><value>false</value></odeNavStructureProperty><odeNavStructureProperty><key>titlePage</key><value>Mètode general</value></odeNavStructureProperty><odeNavStructureProperty><key>visibility</key><value>true</value></odeNavStructureProperty><odeNavStructureProperty><key>highlight</key><value>false</value></odeNavStructureProperty><odeNavStructureProperty><key>description</key><value/></odeNavStructureProperty></odeNavStructureProperties><odePagStructures/></odeNavStructure></odeNavStructures></ode>
